task_manager/__init__.py
task_manager/cli.py
task_manager/manager.py
task_manager/models.py
task_manager_cli-0.1.2.dist-info/METADATA
task_manager_cli-0.1.2.dist-info/WHEEL
task_manager_cli-0.1.2.dist-info/entry_points.txt
task_manager_cli-0.1.2.dist-info/licenses/LICENSE
task_manager_cli-0.1.2.dist-info/RECORD
