Metadata-Version: 2.4
Name: task-manager-cli
Version: 0.1.2
Summary: 一个简单但功能强大的命令行任务管理工具
Project-URL: Homepage, https://github.com/kaleozhou/tasks-manager
Project-URL: Repository, https://github.com/kaleozhou/tasks-manager.git
Project-URL: Issues, https://github.com/kaleozhou/tasks-manager/issues
Author-email: Kaleo Zhou <kaleovip@163.com>
License: MIT License
License-File: LICENSE
Keywords: cli,management,project,task,todo
Classifier: Development Status :: 4 - Beta
Classifier: Environment :: Console
Classifier: Intended Audience :: Developers
Classifier: License :: OSI Approved :: MIT License
Classifier: Operating System :: OS Independent
Classifier: Programming Language :: Python :: 3
Classifier: Programming Language :: Python :: 3.7
Classifier: Programming Language :: Python :: 3.8
Classifier: Programming Language :: Python :: 3.9
Classifier: Programming Language :: Python :: 3.10
Classifier: Programming Language :: Python :: 3.11
Classifier: Topic :: Software Development :: Libraries :: Python Modules
Classifier: Topic :: Utilities
Requires-Python: >=3.7
Requires-Dist: click>=8.0.0
Requires-Dist: pydantic>=2.0.0
Requires-Dist: rich>=10.0.0
